pygmrt/__init__.py
pygmrt/tiles.py
pygmrt-0.1.0.dist-info/licenses/LICENSE
pygmrt-0.1.0.dist-info/METADATA
pygmrt-0.1.0.dist-info/WHEEL
pygmrt-0.1.0.dist-info/top_level.txt
pygmrt-0.1.0.dist-info/RECORD
