Metadata-Version: 2.4
Name: pygmrt
Version: 0.1.0
Summary: A minimal Python package for downloading bathymetry and topography tiles from GMRT
Author-email: Leonard Seydoux <leonard.seydoux@gmail.com>
Maintainer-email: Leonard Seydoux <leonard.seydoux@gmail.com>
License: MIT License
Project-URL: Homepage, https://github.com/leonard-seydoux/pygmrt
Project-URL: Documentation, https://leonard-seydoux.github.io/pygmrt
Project-URL: Repository, https://github.com/leonard-seydoux/pygmrt.git
Project-URL: Bug Tracker, https://github.com/leonard-seydoux/pygmrt/issues
Keywords: bathymetry,topography,gmrt,geospatial,oceanography
Classifier: Development Status :: 4 - Beta
Classifier: Intended Audience :: Science/Research
Classifier: License :: OSI Approved :: MIT License
Classifier: Operating System :: OS Independent
Classifier: Programming Language :: Python :: 3
Classifier: Programming Language :: Python :: 3.11
Classifier: Programming Language :: Python :: 3.12
Classifier: Topic :: Scientific/Engineering :: GIS
Classifier: Topic :: Scientific/Engineering :: Visualization
Requires-Python: >=3.11
License-File: LICENSE
Requires-Dist: requests>=2.32.0
Requires-Dist: rasterio>=1.4.3
Provides-Extra: dev
Requires-Dist: pytest>=7.0.0; extra == "dev"
Requires-Dist: pytest-cov>=4.0.0; extra == "dev"
Requires-Dist: black>=23.0.0; extra == "dev"
Requires-Dist: ruff>=0.1.0; extra == "dev"
Provides-Extra: docs
Requires-Dist: sphinx>=8.2.3; extra == "docs"
Requires-Dist: pydata-sphinx-theme>=0.15.0; extra == "docs"
Requires-Dist: myst-parser>=4.0.0; extra == "docs"
Requires-Dist: nbsphinx>=0.9.0; extra == "docs"
Requires-Dist: sphinx-gallery>=0.18.0; extra == "docs"
Requires-Dist: matplotlib>=3.9.0; extra == "docs"
Requires-Dist: numpy>=1.24.0; extra == "docs"
Requires-Dist: ipykernel>=6.30.1; extra == "docs"
Dynamic: license-file
